CHANGELOG.rst
LICENSE
MANIFEST.in
README.rst
setup.py
anicode/__init__.py
anicode/__main__.py
anicode/__version__.py
anicode/anicode.py
anicode/cli.py
anicode/const.py
anicode/result.py
anicode/utils.py
anicode.egg-info/PKG-INFO
anicode.egg-info/SOURCES.txt
anicode.egg-info/dependency_links.txt
anicode.egg-info/entry_points.txt
anicode.egg-info/requires.txt
anicode.egg-info/top_level.txt
anicode/meta/__init__.py
anicode/sources/__init__.py
anicode/sources/_common.py
anicode/sources/unicode_table.py
tests/__init__.py
tests/test_anicode.py
tests/test_test.py