Metadata-Version: 1.2
Name: anicode
Version: 0.0.1
Summary: A quick unicode search tool
Home-page: https://github.com/stephen-bunn/anicode
Author: Stephen Bunn
Author-email: stephen@bunn.io
License: MIT License
Keywords: anicode
Platform: UNKNOWN
Classifier: Development Status :: 2 - Pre-Alpha
Classifier: Programming Language :: Python :: 3.5
Classifier: Programming Language :: Python :: 3.6
Classifier: Intended Audience :: Developers
Classifier: Operating System :: POSIX
Classifier: Operating System :: MacOS :: MacOS X
Classifier: Natural Language :: English
Requires-Python: >=3.5
